mypackg/__init__.py
mypackg/example.py
mypackg-0.1.dist-info/LICENCE
mypackg-0.1.dist-info/METADATA
mypackg-0.1.dist-info/WHEEL
mypackg-0.1.dist-info/top_level.txt
mypackg-0.1.dist-info/RECORD
